format_k/__init__.py
format_k/main.py
format_k-1.0.0.dist-info/METADATA
format_k-1.0.0.dist-info/WHEEL
format_k-1.0.0.dist-info/entry_points.txt
format_k-1.0.0.dist-info/top_level.txt
format_k-1.0.0.dist-info/RECORD
