Metadata-Version: 2.1
Name: format-k
Version: 1.0.0
Summary: A simple image format converter using Pillow
Home-page: https://github.com/yourusername/image_converter
Author: Your Name
Author-email: your.email@example.com
Classifier: Programming Language :: Python :: 3
Classifier: License :: OSI Approved :: MIT License
Classifier: Operating System :: OS Independent
Requires-Python: >=3.6
Requires-Dist: Pillow
